{
  "themes": {
    "light": {
      "colors": {
        "default": {
          "50": "#f0f4f8",
          "100": "#d9e2ec",
          "200": "#bcccdc",
          "300": "#9fb3c8",
          "400": "#829ab1",
          "500": "#627d98",
          "600": "#486581",
          "700": "#334e68",
          "800": "#243b53",
          "900": "#102a43",
          "foreground": "#000",
          "DEFAULT": "#627d98"
        },
        "primary": {
          "50": "#e3f8ff",
          "100": "#b3ecff",
          "200": "#81defd",
          "300": "#5ed0fa",
          "400": "#40c3f7",
          "500": "#2bb0ed",
          "600": "#1992d4",
          "700": "#127fbf",
          "800": "#0b69a3",
          "900": "#035388",
          "foreground": "#fff",
          "DEFAULT": "#2bb0ed"
        },
        "secondary": {
          "50": "#e6f7ff",
          "100": "#bae3ff",
          "200": "#7cc4fa",
          "300": "#47a3f3",
          "400": "#2186eb",
          "500": "#0967d2",
          "600": "#0552b5",
          "700": "#03449e",
          "800": "#01337d",
          "900": "#002159",
          "foreground": "#fff",
          "DEFAULT": "#0967d2"
        },
        "success": {
          "50": "#e3f9e5",
          "100": "#c1f2c7",
          "200": "#91e697",
          "300": "#51ca58",
          "400": "#31b237",
          "500": "#18981d",
          "600": "#0f8613",
          "700": "#0e7817",
          "800": "#07600e",
          "900": "#05400a",
          "foreground": "#fff",
          "DEFAULT": "#18981d"
        },
        "warning": {
          "50": "#fffbea",
          "100": "#fff3c4",
          "200": "#fce588",
          "300": "#fadb5f",
          "400": "#f7c948",
          "500": "#f0b429",
          "600": "#de911d",
          "700": "#cb6e17",
          "800": "#b44d12",
          "900": "#8d2b0b",
          "foreground": "#000",
          "DEFAULT": "#f0b429"
        },
        "danger": {
          "50": "#ffe3e3",
          "100": "#ffbdbd",
          "200": "#ff9b9b",
          "300": "#f86a6a",
          "400": "#ef4e4e",
          "500": "#e12d39",
          "600": "#cf1124",
          "700": "#ab091e",
          "800": "#8a041a",
          "900": "#610316",
          "foreground": "#fff",
          "DEFAULT": "#e12d39"
        },
        "background": "#f8fafc",
        "foreground": "#334e68",
        "content1": {
          "DEFAULT": "#f0f4f8",
          "foreground": "#334e68"
        },
        "content2": {
          "DEFAULT": "#d9e2ec",
          "foreground": "#334e68"
        },
        "content3": {
          "DEFAULT": "#bcccdc",
          "foreground": "#334e68"
        },
        "content4": {
          "DEFAULT": "#9fb3c8",
          "foreground": "#334e68"
        },
        "focus": "#2bb0ed",
        "overlay": "#000000"
      }
    },
    "dark": {
      "colors": {
        "default": {
          "50": "#0f1c2d",
          "100": "#1e354d",
          "200": "#2d4a6d",
          "300": "#3c5d8d",
          "400": "#4b6fa9",
          "500": "#6384c6",
          "600": "#8ba3d7",
          "700": "#b3c2e7",
          "800": "#dbe1f7",
          "900": "#f5f7fd",
          "foreground": "#fff",
          "DEFAULT": "#4b6fa9"
        },
        "primary": {
          "50": "#0a2e4a",
          "100": "#144a76",
          "200": "#1e67a3",
          "300": "#2884cf",
          "400": "#32a0fc",
          "500": "#57b3fd",
          "600": "#7cc6fd",
          "700": "#a1d9fe",
          "800": "#c6ecfe",
          "900": "#ebf8ff",
          "foreground": "#fff",
          "DEFAULT": "#57b3fd"
        },
        "secondary": {
          "50": "#061633",
          "100": "#0c2a5e",
          "200": "#133f8a",
          "300": "#1953b5",
          "400": "#2068e0",
          "500": "#4382e6",
          "600": "#669cec",
          "700": "#8ab6f2",
          "800": "#add0f8",
          "900": "#d1e9fd",
          "foreground": "#fff",
          "DEFAULT": "#4382e6"
        },
        "success": {
          "50": "#04200a",
          "100": "#093a14",
          "200": "#0e551e",
          "300": "#136f28",
          "400": "#188a32",
          "500": "#25a244",
          "600": "#4dba67",
          "700": "#76d28a",
          "800": "#9fe9ad",
          "900": "#c7ffd1",
          "foreground": "#000",
          "DEFAULT": "#25a244"
        },
        "warning": {
          "50": "#341a03",
          "100": "#5f3306",
          "200": "#8a4d09",
          "300": "#b5660c",
          "400": "#e0800f",
          "500": "#f9a52b",
          "600": "#fbb851",
          "700": "#fdcc78",
          "800": "#fee09e",
          "900": "#fff3c4",
          "foreground": "#000",
          "DEFAULT": "#f9a52b"
        },
        "danger": {
          "50": "#2b0000",
          "100": "#560101",
          "200": "#810202",
          "300": "#ac0303",
          "400": "#d70404",
          "500": "#f42829",
          "600": "#f65354",
          "700": "#f87e7f",
          "800": "#fba9a9",
          "900": "#fdd4d4",
          "foreground": "#fff",
          "DEFAULT": "#f42829"
        },
        "background": "#0a1929",
        "foreground": "#d9e2ec",
        "content1": {
          "DEFAULT": "#102a43",
          "foreground": "#d9e2ec"
        },
        "content2": {
          "DEFAULT": "#1a3e5a",
          "foreground": "#d9e2ec"
        },
        "content3": {
          "DEFAULT": "#245171",
          "foreground": "#d9e2ec"
        },
        "content4": {
          "DEFAULT": "#2e6488",
          "foreground": "#d9e2ec"
        },
        "focus": "#57b3fd",
        "overlay": "#ffffff"
      }
    }
  },
  "layout": {
    "disabledOpacity": "0.5"
  }
}